tidal_per_transformers/__init__.py
tidal_per_transformers/transformers/__init__.py
tidal_per_transformers/transformers/aggregate_transformer.py
tidal_per_transformers/transformers/artifact_id_mapping_by_user_country_transformer.py
tidal_per_transformers/transformers/artist_compound_transformer.py
tidal_per_transformers/transformers/artist_filter_transformer.py
tidal_per_transformers/transformers/artists_struct_filter_transformer.py
tidal_per_transformers/transformers/blazingtext_input_format_transformer.py
tidal_per_transformers/transformers/broadcast_array_intersect_transformer.py
tidal_per_transformers/transformers/clean_text_transformer.py
tidal_per_transformers/transformers/collect_ranked_list_transformer.py
tidal_per_transformers/transformers/collect_ranked_map_transformer.py
tidal_per_transformers/transformers/collect_sessions_transformer.py
tidal_per_transformers/transformers/deduplicate_sequence_transformer.py
tidal_per_transformers/transformers/distinct_sequence_transformer.py
tidal_per_transformers/transformers/distinct_transformer.py
tidal_per_transformers/transformers/diversity_sort_transformer.py
tidal_per_transformers/transformers/drop_columns_transformer.py
tidal_per_transformers/transformers/drop_duplicates_transformer.py
tidal_per_transformers/transformers/filter_dead_and_inactive_artists_transformer.py
tidal_per_transformers/transformers/filter_inactive_users_transformer.py
tidal_per_transformers/transformers/filter_infrequent_seq_transformer.py
tidal_per_transformers/transformers/filter_infrequent_transformer.py
tidal_per_transformers/transformers/filter_matching_text_transformer.py
tidal_per_transformers/transformers/flatten_struct_transformer.py
tidal_per_transformers/transformers/generic_recommendation_formatter_transformer.py
tidal_per_transformers/transformers/join_transformer.py
tidal_per_transformers/transformers/loggable_transformer.py
tidal_per_transformers/transformers/main_artist_compound_mapping_transformer.py
tidal_per_transformers-0.5.0.dist-info/METADATA
tidal_per_transformers-0.5.0.dist-info/WHEEL
tidal_per_transformers-0.5.0.dist-info/licenses/LICENSE
tidal_per_transformers-0.5.0.dist-info/RECORD
