Metadata-Version: 2.4
Name: tidal_per_transformers
Version: 0.5.0
Summary: common transformers used by the tidal personalization team.
License: Apache-2.0
License-File: LICENSE
Author: Loay
Author-email: loay@squareup.com
Requires-Python: >=3.12.0
Classifier: License :: OSI Approved :: Apache Software License
Classifier: Programming Language :: Python :: 3
Classifier: Programming Language :: Python :: 3.12
Classifier: Programming Language :: Python :: 3.13
Classifier: Programming Language :: Python :: 3.14
Requires-Dist: alphabet-detector (==0.0.7)
Requires-Dist: numpy (>=2.1.3,<3.0.0)
Requires-Dist: pandas (>=2.3.2,<3.0.0)
Requires-Dist: pyarrow (>=8.0.0)
Requires-Dist: pyspark (>=4.0.0)
Project-URL: Homepage, https://github.com/tidal-music/tidal-algorithmic-mixes
